totp/__init__.py
totp/__main__.py
totp/config.py
totp/crypt.py
totp/text.py
totp/tui.py
totp/utils.py
totp_tui-0.3.0.dist-info/licenses/LICENSE
totp_tui-0.3.0.dist-info/METADATA
totp_tui-0.3.0.dist-info/WHEEL
totp_tui-0.3.0.dist-info/entry_points.txt
totp_tui-0.3.0.dist-info/top_level.txt
totp_tui-0.3.0.dist-info/RECORD
