Metadata-Version: 2.4
Name: totp-tui
Version: 0.3.0
Summary: TUI utility to generate TOTP codes
Author-email: Guillem Escarpa <85617619+Beeing-Amazing@users.noreply.github.com>
Project-URL: Homepage, https://github.com/Beeing-Amazing/totp
Requires-Python: >=3.13
License-File: LICENSE
Requires-Dist: cryptography>=46.0.3
Requires-Dist: pyperclip>=1.11.0
Dynamic: license-file
